tamil_nlp_package_test/__init__.py
tamil_nlp_package_test/app.log
tamil_nlp_package_test/logger.py
tamil_nlp_package_test/perl_word_tokenizer/ChangeLog
tamil_nlp_package_test/perl_word_tokenizer/INSTALL
tamil_nlp_package_test/perl_word_tokenizer/README
tamil_nlp_package_test/perl_word_tokenizer/data/tam.acr
tamil_nlp_package_test/perl_word_tokenizer/doc/how-prepare-data.txt
tamil_nlp_package_test/perl_word_tokenizer/doc/sample-acronym-data-hin/devanagri-barakhari-utf.txt
tamil_nlp_package_test/perl_word_tokenizer/doc/sample-acronym-data-hin/devanagri-barakhari-wx.txt
tamil_nlp_package_test/perl_word_tokenizer/doc/sample-acronym-data-hin/special-symbols.txt
tamil_nlp_package_test/perl_word_tokenizer/doc/tokenizer_srs_0.1.doc
tamil_nlp_package_test/perl_word_tokenizer/in.txt
tamil_nlp_package_test/perl_word_tokenizer/tests/Input/input.txt
tamil_nlp_package_test/perl_word_tokenizer/tests/Output/tokenizer-indic-1.9_rout_1
tamil_nlp_package_test/perl_word_tokenizer/tests/Output/tokenizer-indic-1.9_rout_10
tamil_nlp_package_test/perl_word_tokenizer/tests/Output/tokenizer-indic-1.9_rout_11
tamil_nlp_package_test/perl_word_tokenizer/tests/Output/tokenizer-indic-1.9_rout_12
tamil_nlp_package_test/perl_word_tokenizer/tests/Output/tokenizer-indic-1.9_rout_13
tamil_nlp_package_test/perl_word_tokenizer/tests/Output/tokenizer-indic-1.9_rout_14
tamil_nlp_package_test/perl_word_tokenizer/tests/Output/tokenizer-indic-1.9_rout_15
tamil_nlp_package_test/perl_word_tokenizer/tests/Output/tokenizer-indic-1.9_rout_16
tamil_nlp_package_test/perl_word_tokenizer/tests/Output/tokenizer-indic-1.9_rout_17
tamil_nlp_package_test/perl_word_tokenizer/tests/Output/tokenizer-indic-1.9_rout_18
tamil_nlp_package_test/perl_word_tokenizer/tests/Output/tokenizer-indic-1.9_rout_19
tamil_nlp_package_test/perl_word_tokenizer/tests/Output/tokenizer-indic-1.9_rout_2
tamil_nlp_package_test/perl_word_tokenizer/tests/Output/tokenizer-indic-1.9_rout_20
tamil_nlp_package_test-1.4.dist-info/LICENSE
tamil_nlp_package_test-1.4.dist-info/METADATA
tamil_nlp_package_test-1.4.dist-info/WHEEL
tamil_nlp_package_test-1.4.dist-info/RECORD
